Workbook

Sheet 1. Operaciones
B3: ID_Operación | C3: Fecha | D3: Cliente | E3: Código Producto | F3: Producto | G3: Categoría | H3: Región | I3: Arancel | J3: País Destino | K3: Clasificación del mercado | L3: Unidades | M3: Precio FOB | N3: Valor FOB | O3: Costo Unitario | P3: Costo Total | Q3: Estado | R3: Utilidad | S3: Margen | T3: Nivel de Operación
B4: EX001 | C4: 46027 | D4: Comercial Maya | E4: P003 | F4: =VLOOKUP(E4,'2. Productos'!$C$4:F8,2,0) -> Miel natural | G4: =VLOOKUP(E4,'2. Productos'!$C$4:F8,3,0) -> Apícola | H4: =VLOOKUP(J4,'3. Mercados'!$C$4:$F$9,2,0) -> Centroamérica | I4: =VLOOKUP(J4,'3. Mercados'!$C$4:$F$9,3,0) -> 0.03 | J4: Guatemala | K4: =VLOOKUP(J4,'3. Mercados'!$C$4:$F$9,4,0) -> Estratégico | L4: 850 | M4: 4.8 | N4: =+L4*M4 -> 4080 | O4: 3.2 | P4: =+L4*O4 -> 2720 | Q4: Embarcado | R4: =+N4-P4 -> 1360 | S4: =+R4/N4 -> 0.33333333 | T4: =IF(S4<=15%, "Baja", IF(S4<=29%, "Mediana", "Alta")) -> Alta
B5: EX002 | C5: 46034 | D5: Global Foods | E5: P001 | F5: =VLOOKUP(E5,'2. Productos'!$C$4:F9,2,0) -> Café especial | G5: =VLOOKUP(E5,'2. Productos'!$C$4:F9,3,0) -> Café | H5: =VLOOKUP(J5,'3. Mercados'!$C$4:$F$9,2,0) -> Norteamérica | I5: =VLOOKUP(J5,'3. Mercados'!$C$4:$F$9,3,0) -> 0.05 | J5: EE.UU. | K5: =VLOOKUP(J5,'3. Mercados'!$C$4:$F$9,4,0) -> Estratégico | L5: 1200 | M5: 6.5 | N5: =+L5*M5 -> 7800 | O5: 4.1 | P5: =+L5*O5 -> 4920 | Q5: Entregado | R5: =+N5-P5 -> 2880 | S5: =+R5/N5 -> 0.36923077 | T5: =IF(S5<=15%, "Baja", IF(S5<=29%, "Mediana", "Alta")) -> Alta
B6: EX003 | C6: 46042 | D6: Distribuidora Tica | E6: P004 | F6: =VLOOKUP(E6,'2. Productos'!$C$4:F10,2,0) -> Maní procesado | G6: =VLOOKUP(E6,'2. Productos'!$C$4:F10,3,0) -> Semillas | H6: =VLOOKUP(J6,'3. Mercados'!$C$4:$F$9,2,0) -> Centroamérica | I6: =VLOOKUP(J6,'3. Mercados'!$C$4:$F$9,3,0) -> 0.02 | J6: Costa Rica | K6: =VLOOKUP(J6,'3. Mercados'!$C$4:$F$9,4,0) -> Estratégico | L6: 650 | M6: 8.2 | N6: =+L6*M6 -> 5330 | O6: 5.9 | P6: =+L6*O6 -> 3835 | Q6: Embarcado | R6: =+N6-P6 -> 1495 | S6: =+R6/N6 -> 0.2804878 | T6: =IF(S6<=15%, "Baja", IF(S6<=29%, "Mediana", "Alta")) -> Mediana
B7: EX004 | C7: 46056 | D7: Iberia Foods | E7: P002 | F7: =VLOOKUP(E7,'2. Productos'!$C$4:F11,2,0) -> Cacao en grano | G7: =VLOOKUP(E7,'2. Productos'!$C$4:F11,3,0) -> Cacao | H7: =VLOOKUP(J7,'3. Mercados'!$C$4:$F$9,2,0) -> Europa | I7: =VLOOKUP(J7,'3. Mercados'!$C$4:$F$9,3,0) -> 0.1 | J7: España | K7: =VLOOKUP(J7,'3. Mercados'!$C$4:$F$9,4,0) -> Potencial | L7: 950 | M7: 7.1 | N7: =+L7*M7 -> 6745 | O7: 4.8 | P7: =+L7*O7 -> 4560 | Q7: Pendiente | R7: =+N7-P7 -> 2185 | S7: =+R7/N7 -> 0.32394366 | T7: =IF(S7<=15%, "Baja", IF(S7<=29%, "Mediana", "Alta")) -> Alta
B8: EX005 | C8: 46068 | D8: Comercial Azteca | E8: P005 | F8: =VLOOKUP(E8,'2. Productos'!$C$4:F12,2,0) -> Aceite de ajonjolí | G8: =VLOOKUP(E8,'2. Productos'!$C$4:F12,3,0) -> Aceites | H8: =VLOOKUP(J8,'3. Mercados'!$C$4:$F$9,2,0) -> Norteamérica | I8: =VLOOKUP(J8,'3. Mercados'!$C$4:$F$9,3,0) -> 0.08 | J8: México | K8: =VLOOKUP(J8,'3. Mercados'!$C$4:$F$9,4,0) -> Potencial | L8: 500 | M8: 12.5 | N8: =+L8*M8 -> 6250 | O8: 8.7 | P8: =+L8*O8 -> 4350 | Q8: Entregado | R8: =+N8-P8 -> 1900 | S8: =+R8/N8 -> 0.304 | T8: =IF(S8<=15%, "Baja", IF(S8<=29%, "Mediana", "Alta")) -> Alta
B9: EX006 | C9: 46081 | D9: Global Foods | E9: P003 | F9: =VLOOKUP(E9,'2. Productos'!$C$4:F13,2,0) -> Miel natural | G9: =VLOOKUP(E9,'2. Productos'!$C$4:F13,3,0) -> Apícola | H9: =VLOOKUP(J9,'3. Mercados'!$C$4:$F$9,2,0) -> Norteamérica | I9: =VLOOKUP(J9,'3. Mercados'!$C$4:$F$9,3,0) -> 0.05 | J9: EE.UU. | K9: =VLOOKUP(J9,'3. Mercados'!$C$4:$F$9,4,0) -> Estratégico | L9: 1400 | M9: 4.8 | N9: =+L9*M9 -> 6720 | O9: 3.2 | P9: =+L9*O9 -> 4480 | Q9: Entregado | R9: =+N9-P9 -> 2240 | S9: =+R9/N9 -> 0.33333333 | T9: =IF(S9<=15%, "Baja", IF(S9<=29%, "Mediana", "Alta")) -> Alta
B10: EX007 | C10: 46089 | D10: Distribuidora Tica | E10: P001 | F10: =VLOOKUP(E10,'2. Productos'!$C$4:F14,2,0) -> Café especial | G10: =VLOOKUP(E10,'2. Productos'!$C$4:F14,3,0) -> Café | H10: =VLOOKUP(J10,'3. Mercados'!$C$4:$F$9,2,0) -> Centroamérica | I10: =VLOOKUP(J10,'3. Mercados'!$C$4:$F$9,3,0) -> 0.02 | J10: Costa Rica | K10: =VLOOKUP(J10,'3. Mercados'!$C$4:$F$9,4,0) -> Estratégico | L10: 900 | M10: 6.5 | N10: =+L10*M10 -> 5850 | O10: 4.1 | P10: =+L10*O10 -> 3690 | Q10: Embarcado | R10: =+N10-P10 -> 2160 | S10: =+R10/N10 -> 0.36923077 | T10: =IF(S10<=15%, "Baja", IF(S10<=29%, "Mediana", "Alta")) -> Alta
B11: EX008 | C11: 46099 | D11: Comercial Maya | E11: P004 | F11: =VLOOKUP(E11,'2. Productos'!$C$4:F15,2,0) -> Maní procesado | G11: =VLOOKUP(E11,'2. Productos'!$C$4:F15,3,0) -> Semillas | H11: =VLOOKUP(J11,'3. Mercados'!$C$4:$F$9,2,0) -> Centroamérica | I11: =VLOOKUP(J11,'3. Mercados'!$C$4:$F$9,3,0) -> 0.03 | J11: Guatemala | K11: =VLOOKUP(J11,'3. Mercados'!$C$4:$F$9,4,0) -> Estratégico | L11: 750 | M11: 8.2 | N11: =+L11*M11 -> 6150 | O11: 5.9 | P11: =+L11*O11 -> 4425 | Q11: Entregado | R11: =+N11-P11 -> 1725 | S11: =+R11/N11 -> 0.2804878 | T11: =IF(S11<=15%, "Baja", IF(S11<=29%, "Mediana", "Alta")) -> Mediana
B12: EX009 | C12: 46106 | D12: Iberia Foods | E12: P005 | F12: =VLOOKUP(E12,'2. Productos'!$C$4:F16,2,0) -> Aceite de ajonjolí | G12: =VLOOKUP(E12,'2. Productos'!$C$4:F16,3,0) -> Aceites | H12: =VLOOKUP(J12,'3. Mercados'!$C$4:$F$9,2,0) -> Europa | I12: =VLOOKUP(J12,'3. Mercados'!$C$4:$F$9,3,0) -> 0.1 | J12: España | K12: =VLOOKUP(J12,'3. Mercados'!$C$4:$F$9,4,0) -> Potencial | L12: 600 | M12: 12.5 | N12: =+L12*M12 -> 7500 | O12: 8.7 | P12: =+L12*O12 -> 5220 | Q12: Embarcado | R12: =+N12-P12 -> 2280 | S12: =+R12/N12 -> 0.304 | T12: =IF(S12<=15%, "Baja", IF(S12<=29%, "Mediana", "Alta")) -> Alta
B13: EX010 | C13: 46114 | D13: Comercial Azteca | E13: P002 | F13: =VLOOKUP(E13,'2. Productos'!$C$4:F17,2,0) -> Cacao en grano | G13: =VLOOKUP(E13,'2. Productos'!$C$4:F17,3,0) -> Cacao | H13: =VLOOKUP(J13,'3. Mercados'!$C$4:$F$9,2,0) -> Norteamérica | I13: =VLOOKUP(J13,'3. Mercados'!$C$4:$F$9,3,0) -> 0.08 | J13: México | K13: =VLOOKUP(J13,'3. Mercados'!$C$4:$F$9,4,0) -> Potencial | L13: 1100 | M13: 7.1 | N13: =+L13*M13 -> 7810 | O13: 4.8 | P13: =+L13*O13 -> 5280 | Q13: Entregado | R13: =+N13-P13 -> 2530 | S13: =+R13/N13 -> 0.32394366 | T13: =IF(S13<=15%, "Baja", IF(S13<=29%, "Mediana", "Alta")) -> Alta
B14: EX011 | C14: 46122 | D14: Global Foods | E14: P004 | F14: =VLOOKUP(E14,'2. Productos'!$C$4:F18,2,0) -> Maní procesado | G14: =VLOOKUP(E14,'2. Productos'!$C$4:F18,3,0) -> Semillas | H14: =VLOOKUP(J14,'3. Mercados'!$C$4:$F$9,2,0) -> Norteamérica | I14: =VLOOKUP(J14,'3. Mercados'!$C$4:$F$9,3,0) -> 0.05 | J14: EE.UU. | K14: =VLOOKUP(J14,'3. Mercados'!$C$4:$F$9,4,0) -> Estratégico | L14: 1300 | M14: 8.2 | N14: =+L14*M14 -> 10660 | O14: 5.9 | P14: =+L14*O14 -> 7670 | Q14: Entregado | R14: =+N14-P14 -> 2990 | S14: =+R14/N14 -> 0.2804878 | T14: =IF(S14<=15%, "Baja", IF(S14<=29%, "Mediana", "Alta")) -> Mediana
B15: EX012 | C15: 46130 | D15: Comercial Maya | E15: P001 | F15: =VLOOKUP(E15,'2. Productos'!$C$4:F19,2,0) -> Café especial | G15: =VLOOKUP(E15,'2. Productos'!$C$4:F19,3,0) -> Café | H15: =VLOOKUP(J15,'3. Mercados'!$C$4:$F$9,2,0) -> Centroamérica | I15: =VLOOKUP(J15,'3. Mercados'!$C$4:$F$9,3,0) -> 0.03 | J15: Guatemala | K15: =VLOOKUP(J15,'3. Mercados'!$C$4:$F$9,4,0) -> Estratégico | L15: 700 | M15: 6.5 | N15: =+L15*M15 -> 4550 | O15: 4.1 | P15: =+L15*O15 -> 2870 | Q15: Pendiente | R15: =+N15-P15 -> 1680 | S15: =+R15/N15 -> 0.36923077 | T15: =IF(S15<=15%, "Baja", IF(S15<=29%, "Mediana", "Alta")) -> Alta
... B103: EX100 | C103: 46150 | D103: Comercial Azteca | E103: P001 | F103: =VLOOKUP(E103,'2. Productos'!$C$4:F107,2,0) -> Café especial | G103: =VLOOKUP(E103,'2. Productos'!$C$4:F107,3,0) -> Café | H103: =VLOOKUP(J103,'3. Mercados'!$C$4:$F$9,2,0) -> Norteamérica | I103: =VLOOKUP(J103,'3. Mercados'!$C$4:$F$9,3,0) -> 0.08 | J103: México | K103: =VLOOKUP(J103,'3. Mercados'!$C$4:$F$9,4,0) -> Potencial | L103: 1170 | M103: 6.5 | N103: =+L103*M103 -> 7605 | O103: 4.1 | P103: =+L103*O103 -> 4797 | Q103: Entregado | R103: =+N103-P103 -> 2808 | S103: =+R103/N103 -> 0.36923077 | T103: =IF(S103<=15%, "Baja", IF(S103<=29%, "Mediana", "Alta")) -> Alta
B106: ¿Cuántas operaciones internacionales se realizaron? | F106: =COUNTA(B4:B103) -> 100
B107: ¿Cuántas operaciones están pendientes? | F107: =COUNTIF(Q4:Q103,"Pendiente") -> 15
B108: ¿Cuánto se exportó hacia Centroamérica? | F108: =SUMIF(H4:H103,"Centroamérica",L4:L103) -> 32720
B110: Etiquetas de fila | C110: Suma de Utilidad
B111: Aceite de ajonjolí | C111: 42218
B112: Cacao en grano | C112: 36800
B113: Café especial | C113: 62832
B114: Maní procesado | C114: 33534
B115: Miel natural | C115: 38688
B116: Total general | C116: 214072
B120: Pregunta | C120: Resultado
B121: Operaciones hacia Estados Unidos | C121: =COUNTIF(J4:J103,"EE.UU.") -> 20
B122: Operaciones pendientes | C122: =COUNTIF(Q4:Q103,"Pendiente") -> 15
B123: Valor FOB hacia Mexico | C123: =SUMIF(J4:J103,"México",N4:N103) -> 120313
B124: Unidades Exportadas hacia Guatemala | C124: =SUMIF(J4:J103,"Guatemala",L4:L103) -> 17130
B125: Valor FOB de Café especial hacia Estados Unidos | C125: =SUMIFS(N4:N103,F4:F103,"Café especial",J4:J103,"EE.UU.") -> 52390
B126: Utilidad de operaciones de Centroamérica | C126: =SUMIFS(R4:R103,H4:H103,"Centroamérica") -> 75241
B129: CONCLUSIONES
B130: 1. Estados Unidos representa el país con mayor valor FOB dentro de las operaciones analizadas, por lo que constituye uno de los mercados más importantes para NicaExport Trading, S.A.
B131: 2. El Café especial destaca entre los productos analizados por generar la mayor utilidad, lo que permite identificarlo como uno de los productos con mayor aporte económico para la empresa.
B132: 3. Norteamérica presenta el mayor valor FOB por región, mientras que las operaciones pendientes requieren seguimiento para mantener un adecuado control de las exportaciones.

Sheet 2. Productos
C2: Catálogo de Productos
C3: Código | D3: Producto | E3: Categoría | F3: Unidad de Medida
C4: P001 | D4: Café especial | E4: Café | F4: Kg
C5: P002 | D5: Cacao en grano | E5: Cacao | F5: Kg
C6: P003 | D6: Miel natural | E6: Apícola | F6: Kg
C7: P004 | D7: Maní procesado | E7: Semillas | F7: Kg
C8: P005 | D8: Aceite de ajonjolí | E8: Aceites | F8: Litro

Sheet 3. Mercados
C2: Mercados
C3: País | D3: Región | E3: Arancel % | F3: Clasificación
C4: EE.UU. | D4: Norteamérica | E4: 0.05 | F4: Estratégico
C5: México | D5: Norteamérica | E5: 0.08 | F5: Potencial
C6: Guatemala | D6: Centroamérica | E6: 0.03 | F6: Estratégico
C7: Costa Rica | D7: Centroamérica | E7: 0.02 | F7: Estratégico
C8: El Salvador | D8: Centroamérica | E8: 0.02 | F8: Potencial
C9: España | D9: Europa | E9: 0.1 | F9: Potencial

Sheet Valor FOB por pais 
A3: Etiquetas de fila | B3: Suma de Valor FOB
A4: Costa Rica | B4: 113544
A5: EE.UU. | B5: 168745
A6: España | B6: 136328
A7: Guatemala | B7: 119335
A8: México | B8: 120313
A9: Total general | B9: 658265
A26: El gráfico muestra el valor FOB generado por cada país de destino. Estados Unidos presenta el mayor valor FOB, seguido por España, México, Guatemala y Costa Rica. Esto permite identificar los mercados que representan una mayor participación en las exportaciones de NicaExport Trading, S.A.

Sheet Utilidad por producto
A3: Etiquetas de fila | B3: Suma de Utilidad
A4: Aceite de ajonjolí | B4: 42218
A5: Cacao en grano | B5: 36800
A6: Café especial | B6: 62832
A7: Maní procesado | B7: 33534
A8: Miel natural | B8: 38688
A9: Total general | B9: 214072
A26: El gráfico muestra la utilidad generada por cada producto. El Café especial presenta la mayor utilidad, seguido por el Aceite de ajonjolí, la Miel natural, el Cacao en grano y el Maní procesado. Esto permite identificar los productos que generan mayores beneficios para la empresa.

Sheet Valor FOB por region
A3: Etiquetas de fila | B3: Suma de Valor FOB
A4: Centroamérica | B4: 232879
A5: Europa | B5: 136328
A6: Norteamérica | B6: 289058
A7: Total general | B7: 658265
A24: El gráfico muestra el valor FOB de las exportaciones según la región de destino. Norteamérica presenta el mayor valor FOB, seguida por Centroamérica y Europa. Esto permite comparar la participación de cada región en las operaciones internacionales de la empresa.
